Librarymu/__init__.py
Librarymu/my_class.py
golden33423319-0.0.2.dist-info/LICENSE.TXT
golden33423319-0.0.2.dist-info/METADATA
golden33423319-0.0.2.dist-info/WHEEL
golden33423319-0.0.2.dist-info/top_level.txt
golden33423319-0.0.2.dist-info/RECORD
