Metadata-Version: 2.1
Name: golden33423319
Version: 0.0.2
Summary: UAS
Home-page: https://github.com/SeladaKeju/gold33423321
Author: Rafi Iqbal
Author-email: <rafiiqbal2407@gmail.com>
License: MIT
Keywords: UAs,COY
Classifier: Development Status :: 1 - Planning
License-File: LICENSE.TXT
